tests
sukimu
