Metadata-Version: 1.1
Name: Sukimu
Version: 2.0.3
Summary: Standardized way to perform CRUD operations with Field validation
Home-page: https://github.com/xethorn/sukimu
Author: Michael Ortali
Author-email: github@xethorn.net
License: MIT
Platform: UNKNOWN
Classifier: Development Status :: Alpha
Classifier: Programming Language :: Python :: 3.4
Classifier: Programming Language :: Python :: 3.5
